napari_time_series_plotter/__init__.py
napari_time_series_plotter/_version.py
napari_time_series_plotter/dock_widgets.py
napari_time_series_plotter/napari.yaml
napari_time_series_plotter/utils.py
napari_time_series_plotter/widgets.py
napari_time_series_plotter/_tests/__init__.py
napari_time_series_plotter/_tests/test_dock_widgets.py
napari_time_series_plotter/_tests/test_utils.py
napari_time_series_plotter/_tests/test_widgets.py
napari_time_series_plotter-0.0.6.dist-info/LICENSE
napari_time_series_plotter-0.0.6.dist-info/METADATA
napari_time_series_plotter-0.0.6.dist-info/WHEEL
napari_time_series_plotter-0.0.6.dist-info/entry_points.txt
napari_time_series_plotter-0.0.6.dist-info/top_level.txt
napari_time_series_plotter-0.0.6.dist-info/RECORD
