Metadata-Version: 2.1
Name: napari-time-series-plotter
Version: 0.0.6
Summary: A Plugin for napari to visualize pixel values over the first dimension (time -> t+3D, t+2D) as graphs.
Home-page: https://github.com/ch-n/napari-time_series_plotter
Author: Christopher Nauroth-Kress
Author-email: nauroth_C@ukw.de
License: BSD-3-Clause
Project-URL: Bug Tracker, https://github.com/ch-n/napari-time_series_plotter/issues
Project-URL: Documentation, https://github.com/ch-n/napari-time_series_plotter#README.md
Project-URL: Source Code, https://github.com/ch-n/napari-time_series_plotter
Project-URL: User Support, https://github.com/ch-n/napari-time_series_plotter/issues
Classifier: Development Status :: 2 - Pre-Alpha
Classifier: Intended Audience :: Developers
Classifier: Framework :: napari
Classifier: Topic :: Software Development :: Testing
Classifier: Programming Language :: Python
Classifier: Programming Language :: Python :: 3
Classifier: Programming Language :: Python :: 3.8
Classifier: Programming Language :: Python :: 3.9
Classifier: Programming Language :: Python :: 3.10
Classifier: Operating System :: OS Independent
Classifier: License :: OSI Approved :: BSD License
Requires-Python: >=3.8
License-File: LICENSE
Requires-Dist: napari-matplotlib (<1.0)
Requires-Dist: numpy
Requires-Dist: pandas
Requires-Dist: qtpy
Provides-Extra: testing
Requires-Dist: tox ; extra == 'testing'
Requires-Dist: pytest ; extra == 'testing'
Requires-Dist: pytest-cov ; extra == 'testing'
Requires-Dist: pytest-qt ; extra == 'testing'
Requires-Dist: napari ; extra == 'testing'
Requires-Dist: pyqt5 ; extra == 'testing'
